numpoisson/__init__.py
numpoisson/errors.py
numpoisson/numpoisson.py
numpoisson/utils.py
numericalpoissongeometry-1.1.1.dist-info/LICENSE.md
numericalpoissongeometry-1.1.1.dist-info/METADATA
numericalpoissongeometry-1.1.1.dist-info/WHEEL
numericalpoissongeometry-1.1.1.dist-info/top_level.txt
numericalpoissongeometry-1.1.1.dist-info/RECORD
