Metadata-Version: 2.1
Name: numericalpoissongeometry
Version: 1.1.1
Summary: A Python Numeric module for (local) calculus on Poisson manifolds
Home-page: https://github.com/appliedgeometry/NumericalPoissonGeometry
Author: Miguel Evangelista-Alvarado, Jose C. Crispín Ruíz, Pablo Suárez-Serrato
Author-email: miguel.eva.alv@gmail.com, jcpanta@im.unam.mx, pablo@im.unam.mx
License: MIT
Platform: UNKNOWN
Classifier: Development Status :: 5 - Production/Stable
Classifier: Programming Language :: Python :: 3 :: Only
Classifier: Programming Language :: Python :: 3.6
Classifier: Programming Language :: Python :: 3.7
Classifier: Programming Language :: Python :: 3.8
Classifier: License :: OSI Approved :: MIT License
Classifier: Operating System :: OS Independent
Classifier: Topic :: Scientific/Engineering :: Mathematics
Classifier: Intended Audience :: Science/Research
Requires-Python: >=3.6, !=2.*
License-File: LICENSE.md
Requires-Dist: sympy
Requires-Dist: numpy
Requires-Dist: torch
Requires-Dist: tensorflow
Requires-Dist: poissongeometry
Requires-Dist: permutation
Requires-Dist: scipy
